reach_rpc/__init__.py
reach_rpc_client-0.1.2.202107081228.dist-info/LICENSE
reach_rpc_client-0.1.2.202107081228.dist-info/METADATA
reach_rpc_client-0.1.2.202107081228.dist-info/WHEEL
reach_rpc_client-0.1.2.202107081228.dist-info/top_level.txt
reach_rpc_client-0.1.2.202107081228.dist-info/RECORD
